MANIFEST.in
scikits/__init__.py
scikits/.libs/libamd-514e2c46.so.2.2
scikits/.libs/libumfpack-a02d2201.so.5.2.0
scikits/.libs/libgfortran-3b85572a.so.3.0.0
scikits/.libs/libopenblasp-r0-135a2122.2.18.so
scikits/.libs/libblas-5861af90.so.3.0.3
scikits/.libs/libgfortran-7904ff66.so.1.0.0
scikits/umfpack/setup.py
scikits/umfpack/__init__.py
scikits/umfpack/version.py
scikits/umfpack/_umfpack.py
scikits/umfpack/umfpack.py
scikits/umfpack/__umfpack.cpython-34m.so
scikits/umfpack/interface.py
scikits/umfpack/tests/test_interface.py
scikits/umfpack/tests/test_umfpack.py
scikits/umfpack/tests/try_umfpack.py
scikit_umfpack-0.3.2.dist-info/WHEEL
scikit_umfpack-0.3.2.dist-info/top_level.txt
scikit_umfpack-0.3.2.dist-info/LICENSE
scikit_umfpack-0.3.2.dist-info/METADATA
scikit_umfpack-0.3.2.dist-info/RECORD
