Metadata-Version: 1.1
Name: scikit-umfpack
Version: 0.3.2
Summary: Python interface to UMFPACK sparse direct solver.
Home-page: https://scikit-umfpack.github.io/scikit-umfpack
Author: Robert Cimrman
Author-email: cimrman3@ntc.zcu.cz
License: BSD
Download-URL: https://scikit-umfpack.github.io/scikit-umfpack
Platform: Linux
Platform: Mac OS-X
Platform: Windows
Classifier: Development Status :: 4 - Beta
Classifier: Environment :: Console
Classifier: Intended Audience :: Developers
Classifier: Intended Audience :: Science/Research
Classifier: License :: OSI Approved :: BSD License
Classifier: Topic :: Scientific/Engineering
Classifier: Programming Language :: C
Classifier: Programming Language :: Python
Classifier: Topic :: Software Development
Classifier: Topic :: Scientific/Engineering
Classifier: Operating System :: Microsoft :: Windows
Classifier: Operating System :: POSIX
Classifier: Operating System :: Unix
Classifier: Operating System :: MacOS
